<?xml version="1.0" encoding="utf-8"?>
<service_provider_sim_configs>
    <service_provider_sim_config sim_config_id="S6.1">
        <mcc>208</mcc>
        <mnc>26</mnc>
        <gid1>31</gid1>
    </service_provider_sim_config>
    <service_provider_sim_config sim_config_id="S6.2">
        <mcc>208</mcc>
        <mnc>01</mnc>
        <gid1>31</gid1>
    </service_provider_sim_config>
    <service_provider_sim_config sim_config_id="S6.3">
        <mcc>208</mcc>
        <mnc>10</mnc>
        <gid1>31</gid1>
    </service_provider_sim_config>
    <service_provider_sim_config sim_config_id="S6.4">
        <mcc>208</mcc>
        <mnc>20</mnc>
        <gid1>31</gid1>
    </service_provider_sim_config>
    <service_provider_sim_config sim_config_id="S6.5">
        <mcc>208</mcc>
        <mnc>26</mnc>
        <gid1>4E</gid1>
    </service_provider_sim_config>
    <service_provider_sim_config sim_config_id="S6.6">
        <mcc>208</mcc>
        <mnc>01</mnc>
        <gid1>4E</gid1>
    </service_provider_sim_config>
    <service_provider_sim_config sim_config_id="S6.7">
        <mcc>208</mcc>
        <mnc>10</mnc>
        <gid1>4E</gid1>
    </service_provider_sim_config>
    <service_provider_sim_config sim_config_id="S6.8">
        <mcc>208</mcc>
        <mnc>20</mnc>
        <gid1>4E</gid1>
    </service_provider_sim_config>
    <service_provider_sim_config sim_config_id="S6.9">
        <mcc>206</mcc>
        <mnc>01</mnc>
        <gid1>4E</gid1>
    </service_provider_sim_config>
    <service_provider_sim_config sim_config_id="S6.10">
        <mcc>206</mcc>
        <mnc>10</mnc>
        <gid1>4E</gid1>
    </service_provider_sim_config>
    <service_provider_sim_config sim_config_id="S6.11">
        <mcc>208</mcc>
        <mnc>01</mnc>
        <sp>C le Mobile</sp>
    </service_provider_sim_config>
    <service_provider_sim_config sim_config_id="S6.12">
        <mcc>208</mcc>
        <mnc>01</mnc>
        <sp>C le Mobile</sp>
        <gid1>4E</gid1>
    </service_provider_sim_config>
    <service_provider_sim_config sim_config_id="S6.13">
        <mcc>206</mcc>
        <mnc>01</mnc>
        <gid1>4E524A31</gid1>
    </service_provider_sim_config>
    <service_provider_sim_config sim_config_id="S7.1">
        <mcc>208</mcc>
        <mnc>20</mnc>
    </service_provider_sim_config>
    <service_provider_sim_config sim_config_id="S7.2">
        <mcc>208</mcc>
        <mnc>20</mnc>
        <sp>Bouygues Telecom</sp>
    </service_provider_sim_config>
    <service_provider_sim_config sim_config_id="S11.2">
        <mcc>208</mcc>
        <mnc>01</mnc>
        <gid1>FF</gid1>
    </service_provider_sim_config>
    <service_provider_sim_config sim_config_id="S11.3">
        <mcc>208</mcc>
        <mnc>01</mnc>
        <sp>Orange F</sp>
        <gid1>FF</gid1>
    </service_provider_sim_config>
    <service_provider_sim_config sim_config_id="S11.4">
        <mcc>208</mcc>
        <mnc>01</mnc>
        <gid1>ffffffff</gid1>
    </service_provider_sim_config>
    <service_provider_sim_config sim_config_id="S11.5">
        <mcc>208</mcc>
        <mnc>01</mnc>
        <sp>Orange F</sp>
    </service_provider_sim_config>
    <service_provider_sim_config sim_config_id="S12.1">
        <mcc>208</mcc>
        <mnc>10</mnc>
    </service_provider_sim_config>
    <service_provider_sim_config sim_config_id="S12.2">
        <mcc>208</mcc>
        <mnc>09</mnc>
    </service_provider_sim_config>
    <service_provider_sim_config sim_config_id="S20.1">
        <mcc>234</mcc>
        <mnc>30</mnc>
    </service_provider_sim_config>
    <service_provider_sim_config sim_config_id="S21.1">
        <mcc>234</mcc>
        <mnc>20</mnc>
        <gid1>0303</gid1>
    </service_provider_sim_config>
    <service_provider_sim_config sim_config_id="S21.2">
        <mcc>235</mcc>
        <mnc>94</mnc>
    </service_provider_sim_config>
    <service_provider_sim_config sim_config_id="S21.3">
        <mcc>234</mcc>
        <mnc>20</mnc>
        <gid1>0305</gid1>
    </service_provider_sim_config>
    <service_provider_sim_config sim_config_id="S21.4">
        <mcc>234</mcc>
        <mnc>20</mnc>
        <gid1>0309</gid1>
    </service_provider_sim_config>
    <service_provider_sim_config sim_config_id="S21.5">
        <mcc>234</mcc>
        <mnc>20</mnc>
        <gid1>0310</gid1>
    </service_provider_sim_config>
    <service_provider_sim_config sim_config_id="S22.1">
        <mcc>234</mcc>
        <mnc>30</mnc>
        <gid1>28</gid1>
    </service_provider_sim_config>
    <service_provider_sim_config sim_config_id="S22.2">
        <mcc>234</mcc>
        <mnc>30</mnc>
        <sp>Virgin</sp>
    </service_provider_sim_config>
    <service_provider_sim_config sim_config_id="S22.3">
        <mcc>234</mcc>
        <mnc>38</mnc>
    </service_provider_sim_config>
    <service_provider_sim_config sim_config_id="S22.4">
        <mcc>206</mcc>
        <mnc>01</mnc>
        <gid1>28</gid1>
    </service_provider_sim_config>
    <service_provider_sim_config sim_config_id="S23.1">
        <mcc>234</mcc>
        <mnc>10</mnc>
    </service_provider_sim_config>
    <service_provider_sim_config sim_config_id="S23.2">
        <mcc>234</mcc>
        <mnc>10</mnc>
        <gid1>0A</gid1>
    </service_provider_sim_config>
    <service_provider_sim_config sim_config_id="S23.3">
        <mcc>234</mcc>
        <mnc>10</mnc>
        <sp>giffgaff</sp>
    </service_provider_sim_config>
    <service_provider_sim_config sim_config_id="S26.1">
        <mcc>272</mcc>
        <mnc>01</mnc>
    </service_provider_sim_config>
    <service_provider_sim_config sim_config_id="S28.1">
        <mcc>272</mcc>
        <mnc>03</mnc>
    </service_provider_sim_config>
    <service_provider_sim_config sim_config_id="S31.1">
        <mcc>228</mcc>
        <mnc>01</mnc>
    </service_provider_sim_config>
    <service_provider_sim_config sim_config_id="S32.1">
        <mcc>228</mcc>
        <mnc>03</mnc>
    </service_provider_sim_config>
    <service_provider_sim_config sim_config_id="S33.1">
        <mcc>228</mcc>
        <mnc>02</mnc>
    </service_provider_sim_config>
    <service_provider_sim_config sim_config_id="S36.1">
        <mcc>452</mcc>
        <mnc>02</mnc>
    </service_provider_sim_config>
    <service_provider_sim_config sim_config_id="S37.1">
        <mcc>452</mcc>
        <mnc>01</mnc>
    </service_provider_sim_config>
    <service_provider_sim_config sim_config_id="S38.1">
        <mcc>505</mcc>
        <mnc>01</mnc>
    </service_provider_sim_config>
    <service_provider_sim_config sim_config_id="S39.14">
        <mcc>505</mcc>
        <mnc>02</mnc>
    </service_provider_sim_config>
    <service_provider_sim_config sim_config_id="S40.2">
        <mcc>505</mcc>
        <mnc>03</mnc>
    </service_provider_sim_config>
    <service_provider_sim_config sim_config_id="S41.5">
        <mcc>505</mcc>
        <mnc>02</mnc>
        <imsi>505029\d*</imsi>
    </service_provider_sim_config>
    <service_provider_sim_config sim_config_id="S43.1">
        <mcc>525</mcc>
        <mnc>01</mnc>
    </service_provider_sim_config>
    <service_provider_sim_config sim_config_id="S44.1">
        <mcc>525</mcc>
        <mnc>03</mnc>
    </service_provider_sim_config>
    <service_provider_sim_config sim_config_id="S45.1">
        <mcc>525</mcc>
        <mnc>05</mnc>
    </service_provider_sim_config>
    <service_provider_sim_config sim_config_id="S46.1">
        <mcc>502</mcc>
        <mnc>16</mnc>
    </service_provider_sim_config>
    <service_provider_sim_config sim_config_id="S47.1">
        <mcc>502</mcc>
        <mnc>12</mnc>
    </service_provider_sim_config>
    <service_provider_sim_config sim_config_id="S47.2">
        <mcc>502</mcc>
        <mnc>17</mnc>
    </service_provider_sim_config>
    <service_provider_sim_config sim_config_id="S48.1">
        <mcc>502</mcc>
        <mnc>19</mnc>
    </service_provider_sim_config>
    <service_provider_sim_config sim_config_id="S50.1">
        <mcc>515</mcc>
        <mnc>03</mnc>
    </service_provider_sim_config>
    <service_provider_sim_config sim_config_id="S52.1">
        <mcc>334</mcc>
        <mnc>020</mnc>
    </service_provider_sim_config>
    <service_provider_sim_config sim_config_id="S53.1">
        <mcc>334</mcc>
        <mnc>030</mnc>
    </service_provider_sim_config>
    <service_provider_sim_config sim_config_id="S54.1">
        <mcc>240</mcc>
        <mnc>01</mnc>
        <sp>Telia</sp>
    </service_provider_sim_config>
    <service_provider_sim_config sim_config_id="S55.3">
        <mcc>240</mcc>
        <mnc>07</mnc>
        <imsi>^24007\s?(([0-5]|[7-9])|600).*</imsi>
    </service_provider_sim_config>
    <service_provider_sim_config sim_config_id="S57.1">
        <mcc>240</mcc>
        <mnc>01</mnc>
        <sp>halebop</sp>
    </service_provider_sim_config>
    <service_provider_sim_config sim_config_id="S58.1">
        <mcc>240</mcc>
        <mnc>08</mnc>
    </service_provider_sim_config>
    <service_provider_sim_config sim_config_id="S59.1">
        <mcc>240</mcc>
        <mnc>02</mnc>
    </service_provider_sim_config>
    <service_provider_sim_config sim_config_id="S59.2">
        <mcc>240</mcc>
        <mnc>02</mnc>
        <sp>3</sp>
    </service_provider_sim_config>
    <service_provider_sim_config sim_config_id="S69.1">
        <mcc>214</mcc>
        <mnc>07</mnc>
    </service_provider_sim_config>
    <service_provider_sim_config sim_config_id="S70.1">
        <mcc>214</mcc>
        <mnc>01</mnc>
    </service_provider_sim_config>
    <service_provider_sim_config sim_config_id="S72.1">
        <mcc>268</mcc>
        <mnc>03</mnc>
    </service_provider_sim_config>
    <service_provider_sim_config sim_config_id="S73.1">
        <mcc>268</mcc>
        <mnc>06</mnc>
    </service_provider_sim_config>
    <service_provider_sim_config sim_config_id="S74.1">
        <mcc>268</mcc>
        <mnc>01</mnc>
    </service_provider_sim_config>
    <service_provider_sim_config sim_config_id="S74.2">
        <mcc>268</mcc>
        <mnc>89</mnc>
    </service_provider_sim_config>
    <service_provider_sim_config sim_config_id="S75.1">
        <mcc>262</mcc>
        <mnc>02</mnc>
    </service_provider_sim_config>
    <service_provider_sim_config sim_config_id="S75.2">
        <mcc>262</mcc>
        <mnc>09</mnc>
    </service_provider_sim_config>
    <service_provider_sim_config sim_config_id="S77.1">
        <mcc>262</mcc>
        <mnc>07</mnc>
    </service_provider_sim_config>
    <service_provider_sim_config sim_config_id="S77.2">
        <mcc>262</mcc>
        <mnc>03</mnc>
    </service_provider_sim_config>
    <service_provider_sim_config sim_config_id="S77.3">
        <mcc>262</mcc>
        <mnc>77</mnc>
    </service_provider_sim_config>
    <service_provider_sim_config sim_config_id="S81.1">
        <mcc>520</mcc>
        <mnc>03</mnc>
    </service_provider_sim_config>
    <service_provider_sim_config sim_config_id="S82.1">
        <mcc>520</mcc>
        <mnc>18</mnc>
    </service_provider_sim_config>
    <service_provider_sim_config sim_config_id="S82.2">
        <mcc>520</mcc>
        <mnc>05</mnc>
    </service_provider_sim_config>
    <service_provider_sim_config sim_config_id="S84.1">
        <mcc>722</mcc>
        <mnc>34</mnc>
    </service_provider_sim_config>
    <service_provider_sim_config sim_config_id="S84.2">
        <mcc>722</mcc>
        <mnc>341</mnc>
    </service_provider_sim_config>
    <service_provider_sim_config sim_config_id="S85.1">
        <mcc>722</mcc>
        <mnc>310</mnc>
    </service_provider_sim_config>
    <service_provider_sim_config sim_config_id="S91.1">
        <mcc>722</mcc>
        <mnc>07</mnc>
    </service_provider_sim_config>
    <service_provider_sim_config sim_config_id="S98.1">
        <mcc>206</mcc>
        <mnc>10</mnc>
    </service_provider_sim_config>
    <service_provider_sim_config sim_config_id="S98.2">
        <mcc>206</mcc>
        <mnc>10</mnc>
        <sp>Orange B</sp>
    </service_provider_sim_config>
    <service_provider_sim_config sim_config_id="S114.1">
        <mcc>234</mcc>
        <mnc>15</mnc>
    </service_provider_sim_config>
    <service_provider_sim_config sim_config_id="S120.1">
        <mcc>238</mcc>
        <mnc>06</mnc>
    </service_provider_sim_config>
    <service_provider_sim_config sim_config_id="S122.1">
        <mcc>238</mcc>
        <mnc>02</mnc>
    </service_provider_sim_config>
    <service_provider_sim_config sim_config_id="S123.1">
        <mcc>238</mcc>
        <mnc>01</mnc>
    </service_provider_sim_config>
    <service_provider_sim_config sim_config_id="S125.1">
        <mcc>238</mcc>
        <mnc>20</mnc>
        <sp>TELIA DK</sp>
    </service_provider_sim_config>
    <service_provider_sim_config sim_config_id="S125.2">
        <mcc>238</mcc>
        <mnc>20</mnc>
    </service_provider_sim_config>
    <service_provider_sim_config sim_config_id="S132.1">
        <mcc>222</mcc>
        <mnc>01</mnc>
    </service_provider_sim_config>
    <service_provider_sim_config sim_config_id="S133.2">
        <mcc>222</mcc>
        <mnc>99</mnc>
        <gid1>0000000000</gid1>
    </service_provider_sim_config>
    <service_provider_sim_config sim_config_id="S133.3">
        <mcc>222</mcc>
        <mnc>88</mnc>
        <gid1>0000000099</gid1>
    </service_provider_sim_config>
    <service_provider_sim_config sim_config_id="S133.4">
        <mcc>222</mcc>
        <mnc>88</mnc>
        <imsi>^22288\s?([^2|^8]).*</imsi>
    </service_provider_sim_config>
    <service_provider_sim_config sim_config_id="S134.1">
        <mcc>222</mcc>
        <mnc>99</mnc>
    </service_provider_sim_config>
    <service_provider_sim_config sim_config_id="S135.1">
        <mcc>222</mcc>
        <mnc>10</mnc>
    </service_provider_sim_config>
    <service_provider_sim_config sim_config_id="S136.1">
        <mcc>232</mcc>
        <mnc>01</mnc>
    </service_provider_sim_config>
    <service_provider_sim_config sim_config_id="S137.1">
        <mcc>232</mcc>
        <mnc>03</mnc>
    </service_provider_sim_config>
    <service_provider_sim_config sim_config_id="S137.2">
        <mcc>232</mcc>
        <mnc>04</mnc>
    </service_provider_sim_config>
    <service_provider_sim_config sim_config_id="S139.1">
        <mcc>232</mcc>
        <mnc>07</mnc>
    </service_provider_sim_config>
    <service_provider_sim_config sim_config_id="S140.1">
        <mcc>232</mcc>
        <mnc>10</mnc>
    </service_provider_sim_config>
    <service_provider_sim_config sim_config_id="S140.2">
        <mcc>232</mcc>
        <mnc>05</mnc>
    </service_provider_sim_config>
    <service_provider_sim_config sim_config_id="S140.3">
        <mcc>232</mcc>
        <mnc>14</mnc>
    </service_provider_sim_config>
    <service_provider_sim_config sim_config_id="S148.1">
        <mcc>510</mcc>
        <mnc>10</mnc>
    </service_provider_sim_config>
    <service_provider_sim_config sim_config_id="S149.1">
        <mcc>510</mcc>
        <mnc>11</mnc>
    </service_provider_sim_config>
    <service_provider_sim_config sim_config_id="S149.2">
        <mcc>510</mcc>
        <mnc>08</mnc>
    </service_provider_sim_config>
    <service_provider_sim_config sim_config_id="S159.1">
        <mcc>530</mcc>
        <mnc>01</mnc>
    </service_provider_sim_config>
    <service_provider_sim_config sim_config_id="S162.6">
        <mcc>302</mcc>
        <mnc>720</mnc>
    </service_provider_sim_config>
    <service_provider_sim_config sim_config_id="S163.2">
        <mcc>302</mcc>
        <mnc>370</mnc>
    </service_provider_sim_config>
    <service_provider_sim_config sim_config_id="S173.1">
        <mcc>230</mcc>
        <mnc>02</mnc>
    </service_provider_sim_config>
    <service_provider_sim_config sim_config_id="S174.1">
        <mcc>230</mcc>
        <mnc>03</mnc>
        <sp>Vodafone CZ</sp>
    </service_provider_sim_config>
    <service_provider_sim_config sim_config_id="S175.1">
        <mcc>230</mcc>
        <mnc>01</mnc>
    </service_provider_sim_config>
    <service_provider_sim_config sim_config_id="S176.1">
        <mcc>219</mcc>
        <mnc>01</mnc>
    </service_provider_sim_config>
    <service_provider_sim_config sim_config_id="S179.1">
        <mcc>216</mcc>
        <mnc>01</mnc>
    </service_provider_sim_config>
    <service_provider_sim_config sim_config_id="S180.1">
        <mcc>216</mcc>
        <mnc>30</mnc>
    </service_provider_sim_config>
    <service_provider_sim_config sim_config_id="S181.1">
        <mcc>216</mcc>
        <mnc>70</mnc>
    </service_provider_sim_config>
    <service_provider_sim_config sim_config_id="S185.1">
        <mcc>260</mcc>
        <mnc>01</mnc>
    </service_provider_sim_config>
    <service_provider_sim_config sim_config_id="S187.1">
        <mcc>260</mcc>
        <mnc>03</mnc>
        <sp>Orange</sp>
    </service_provider_sim_config>
    <service_provider_sim_config sim_config_id="S187.5">
        <mcc>260</mcc>
        <mnc>03</mnc>
        <sp>Orange PL</sp>
    </service_provider_sim_config>
    <service_provider_sim_config sim_config_id="S187.6">
        <mcc>260</mcc>
        <mnc>03</mnc>
    </service_provider_sim_config>
    <service_provider_sim_config sim_config_id="S187.7">
        <mcc>260</mcc>
        <mnc>03</mnc>
        <sp>nju</sp>
    </service_provider_sim_config>
    <service_provider_sim_config sim_config_id="S188.1">
        <mcc>218</mcc>
        <mnc>90</mnc>
    </service_provider_sim_config>
    <service_provider_sim_config sim_config_id="S189.1">
        <mcc>218</mcc>
        <mnc>03</mnc>
    </service_provider_sim_config>
    <service_provider_sim_config sim_config_id="S190.1">
        <mcc>218</mcc>
        <mnc>05</mnc>
    </service_provider_sim_config>
    <service_provider_sim_config sim_config_id="S191.1">
        <mcc>220</mcc>
        <mnc>01</mnc>
    </service_provider_sim_config>
    <service_provider_sim_config sim_config_id="S194.1">
        <mcc>220</mcc>
        <mnc>03</mnc>
    </service_provider_sim_config>
    <service_provider_sim_config sim_config_id="S202.1">
        <mcc>293</mcc>
        <mnc>41</mnc>
    </service_provider_sim_config>
    <service_provider_sim_config sim_config_id="S203.1">
        <mcc>293</mcc>
        <mnc>40</mnc>
    </service_provider_sim_config>
    <service_provider_sim_config sim_config_id="S205.1">
        <mcc>231</mcc>
        <mnc>01</mnc>
        <sp>Orange</sp>
    </service_provider_sim_config>
    <service_provider_sim_config sim_config_id="S206.1">
        <mcc>231</mcc>
        <mnc>02</mnc>
    </service_provider_sim_config>
    <service_provider_sim_config sim_config_id="S212.1">
        <mcc>206</mcc>
        <mnc>01</mnc>
    </service_provider_sim_config>
    <service_provider_sim_config sim_config_id="S215.1">
        <mcc>270</mcc>
        <mnc>01</mnc>
    </service_provider_sim_config>
    <service_provider_sim_config sim_config_id="S218.1">
        <mcc>204</mcc>
        <mnc>08</mnc>
    </service_provider_sim_config>
    <service_provider_sim_config sim_config_id="S219.1">
        <mcc>204</mcc>
        <mnc>04</mnc>
    </service_provider_sim_config>
    <service_provider_sim_config sim_config_id="S221.1">
        <mcc>204</mcc>
        <mnc>16</mnc>
        <sp>T-Mobile NL</sp>
    </service_provider_sim_config>
    <service_provider_sim_config sim_config_id="S221.4">
        <mcc>204</mcc>
        <mnc>16</mnc>
        <sp>T-Mobile  NL</sp>
    </service_provider_sim_config>
    <service_provider_sim_config sim_config_id="S221.5">
        <mcc>204</mcc>
        <mnc>20</mnc>
        <sp>T-Mobile  NL</sp>
    </service_provider_sim_config>
    <service_provider_sim_config sim_config_id="S228.1">
        <mcc>226</mcc>
        <mnc>01</mnc>
    </service_provider_sim_config>
    <service_provider_sim_config sim_config_id="S230.1">
        <mcc>226</mcc>
        <mnc>10</mnc>
        <sp>orange</sp>
    </service_provider_sim_config>
    <service_provider_sim_config sim_config_id="S230.2">
        <mcc>226</mcc>
        <mnc>10</mnc>
    </service_provider_sim_config>
    <service_provider_sim_config sim_config_id="S232.1">
        <mcc>284</mcc>
        <mnc>05</mnc>
    </service_provider_sim_config>
    <service_provider_sim_config sim_config_id="S236.1">
        <mcc>286</mcc>
        <mnc>01</mnc>
        <sp>Turkcell</sp>
    </service_provider_sim_config>
    <service_provider_sim_config sim_config_id="S236.2">
        <mcc>286</mcc>
        <mnc>01</mnc>
    </service_provider_sim_config>
    <service_provider_sim_config sim_config_id="S237.3">
        <mcc>286</mcc>
        <mnc>02</mnc>
        <sp>Vodafone TR</sp>
    </service_provider_sim_config>
    <service_provider_sim_config sim_config_id="S237.4">
        <mcc>286</mcc>
        <mnc>02</mnc>
    </service_provider_sim_config>
    <service_provider_sim_config sim_config_id="S238.1">
        <mcc>286</mcc>
        <mnc>03</mnc>
        <sp>Avea</sp>
    </service_provider_sim_config>
    <service_provider_sim_config sim_config_id="S238.2">
        <mcc>286</mcc>
        <mnc>04</mnc>
        <sp>Avea</sp>
    </service_provider_sim_config>
    <service_provider_sim_config sim_config_id="S238.3">
        <mcc>286</mcc>
        <mnc>03</mnc>
    </service_provider_sim_config>
    <service_provider_sim_config sim_config_id="S238.4">
        <mcc>286</mcc>
        <mnc>04</mnc>
    </service_provider_sim_config>
    <service_provider_sim_config sim_config_id="S241.1">
        <mcc>425</mcc>
        <mnc>02</mnc>
        <sp>Cellcom</sp>
    </service_provider_sim_config>
    <service_provider_sim_config sim_config_id="S249.1">
        <mcc>246</mcc>
        <mnc>01</mnc>
    </service_provider_sim_config>
    <service_provider_sim_config sim_config_id="S251.1">
        <mcc>246</mcc>
        <mnc>03</mnc>
    </service_provider_sim_config>
    <service_provider_sim_config sim_config_id="S252.1">
        <mcc>248</mcc>
        <mnc>01</mnc>
    </service_provider_sim_config>
    <service_provider_sim_config sim_config_id="S253.1">
        <mcc>248</mcc>
        <mnc>02</mnc>
    </service_provider_sim_config>
    <service_provider_sim_config sim_config_id="S254.1">
        <mcc>248</mcc>
        <mnc>03</mnc>
    </service_provider_sim_config>
    <service_provider_sim_config sim_config_id="S255.1">
        <mcc>244</mcc>
        <mnc>91</mnc>
    </service_provider_sim_config>
    <service_provider_sim_config sim_config_id="S256.1">
        <mcc>244</mcc>
        <mnc>05</mnc>
    </service_provider_sim_config>
    <service_provider_sim_config sim_config_id="S256.2">
        <mcc>244</mcc>
        <mnc>21</mnc>
    </service_provider_sim_config>
    <service_provider_sim_config sim_config_id="S257.1">
        <mcc>244</mcc>
        <mnc>12</mnc>
    </service_provider_sim_config>
    <service_provider_sim_config sim_config_id="S257.2">
        <mcc>244</mcc>
        <mnc>13</mnc>
    </service_provider_sim_config>
    <service_provider_sim_config sim_config_id="S260.1">
        <mcc>242</mcc>
        <mnc>01</mnc>
    </service_provider_sim_config>
    <service_provider_sim_config sim_config_id="S261.1">
        <mcc>242</mcc>
        <mnc>02</mnc>
    </service_provider_sim_config>
    <service_provider_sim_config sim_config_id="S263.1">
        <mcc>310</mcc>
        <mnc>410</mnc>
    </service_provider_sim_config>
    <service_provider_sim_config sim_config_id="S263.2">
        <mcc>310</mcc>
        <mnc>150</mnc>
    </service_provider_sim_config>
    <service_provider_sim_config sim_config_id="S263.3">
        <mcc>310</mcc>
        <mnc>170</mnc>
    </service_provider_sim_config>
    <service_provider_sim_config sim_config_id="S263.4">
        <mcc>310</mcc>
        <mnc>560</mnc>
    </service_provider_sim_config>
    <service_provider_sim_config sim_config_id="S263.5">
        <mcc>310</mcc>
        <mnc>680</mnc>
    </service_provider_sim_config>
    <service_provider_sim_config sim_config_id="S263.6">
        <mcc>310</mcc>
        <mnc>380</mnc>
    </service_provider_sim_config>
    <service_provider_sim_config sim_config_id="S263.7">
        <mcc>310</mcc>
        <mnc>070</mnc>
    </service_provider_sim_config>
    <service_provider_sim_config sim_config_id="S263.8">
        <mcc>310</mcc>
        <mnc>090</mnc>
    </service_provider_sim_config>
    <service_provider_sim_config sim_config_id="S263.9">
        <mcc>310</mcc>
        <mnc>030</mnc>
    </service_provider_sim_config>
    <service_provider_sim_config sim_config_id="S263.10">
        <mcc>310</mcc>
        <mnc>280</mnc>
    </service_provider_sim_config>
    <service_provider_sim_config sim_config_id="S264.1">
        <mcc>310</mcc>
        <mnc>160</mnc>
    </service_provider_sim_config>
    <service_provider_sim_config sim_config_id="S264.2">
        <mcc>310</mcc>
        <mnc>200</mnc>
    </service_provider_sim_config>
    <service_provider_sim_config sim_config_id="S264.3">
        <mcc>310</mcc>
        <mnc>210</mnc>
    </service_provider_sim_config>
    <service_provider_sim_config sim_config_id="S264.4">
        <mcc>310</mcc>
        <mnc>220</mnc>
    </service_provider_sim_config>
    <service_provider_sim_config sim_config_id="S264.5">
        <mcc>310</mcc>
        <mnc>230</mnc>
    </service_provider_sim_config>
    <service_provider_sim_config sim_config_id="S264.6">
        <mcc>310</mcc>
        <mnc>240</mnc>
    </service_provider_sim_config>
    <service_provider_sim_config sim_config_id="S264.7">
        <mcc>310</mcc>
        <mnc>250</mnc>
    </service_provider_sim_config>
    <service_provider_sim_config sim_config_id="S264.8">
        <mcc>310</mcc>
        <mnc>260</mnc>
    </service_provider_sim_config>
    <service_provider_sim_config sim_config_id="S264.9">
        <mcc>310</mcc>
        <mnc>270</mnc>
    </service_provider_sim_config>
    <service_provider_sim_config sim_config_id="S264.10">
        <mcc>310</mcc>
        <mnc>300</mnc>
    </service_provider_sim_config>
    <service_provider_sim_config sim_config_id="S264.11">
        <mcc>310</mcc>
        <mnc>310</mnc>
    </service_provider_sim_config>
    <service_provider_sim_config sim_config_id="S264.12">
        <mcc>310</mcc>
        <mnc>490</mnc>
    </service_provider_sim_config>
    <service_provider_sim_config sim_config_id="S264.13">
        <mcc>310</mcc>
        <mnc>530</mnc>
    </service_provider_sim_config>
    <service_provider_sim_config sim_config_id="S264.14">
        <mcc>310</mcc>
        <mnc>590</mnc>
    </service_provider_sim_config>
    <service_provider_sim_config sim_config_id="S264.15">
        <mcc>310</mcc>
        <mnc>640</mnc>
    </service_provider_sim_config>
    <service_provider_sim_config sim_config_id="S264.16">
        <mcc>310</mcc>
        <mnc>660</mnc>
    </service_provider_sim_config>
    <service_provider_sim_config sim_config_id="S264.17">
        <mcc>310</mcc>
        <mnc>800</mnc>
    </service_provider_sim_config>
    <service_provider_sim_config sim_config_id="S264.18">
        <mcc>310</mcc>
        <mnc>580</mnc>
    </service_provider_sim_config>
    <service_provider_sim_config sim_config_id="S267.1">
        <mcc>647</mcc>
        <mnc>10</mnc>
    </service_provider_sim_config>
    <service_provider_sim_config sim_config_id="S273.1">
        <mcc>202</mcc>
        <mnc>01</mnc>
    </service_provider_sim_config>
    <service_provider_sim_config sim_config_id="S275.1">
        <mcc>202</mcc>
        <mnc>05</mnc>
    </service_provider_sim_config>
    <service_provider_sim_config sim_config_id="S277.1">
        <mcc>466</mcc>
        <mnc>92</mnc>
    </service_provider_sim_config>
    <service_provider_sim_config sim_config_id="S278.1">
        <mcc>466</mcc>
        <mnc>01</mnc>
    </service_provider_sim_config>
    <service_provider_sim_config sim_config_id="S280.1">
        <mcc>466</mcc>
        <mnc>97</mnc>
    </service_provider_sim_config>
    <service_provider_sim_config sim_config_id="S283.1">
        <mcc>466</mcc>
        <mnc>89</mnc>
    </service_provider_sim_config>
    <service_provider_sim_config sim_config_id="S284.1">
        <mcc>460</mcc>
        <mnc>00</mnc>
    </service_provider_sim_config>
    <service_provider_sim_config sim_config_id="S284.2">
        <mcc>460</mcc>
        <mnc>02</mnc>
    </service_provider_sim_config>
    <service_provider_sim_config sim_config_id="S284.3">
        <mcc>460</mcc>
        <mnc>07</mnc>
    </service_provider_sim_config>
    <service_provider_sim_config sim_config_id="S284.4">
        <mcc>460</mcc>
        <mnc>08</mnc>
    </service_provider_sim_config>
    <service_provider_sim_config sim_config_id="S284.5">
        <mcc>460</mcc>
        <mnc>04</mnc>
    </service_provider_sim_config>
    <service_provider_sim_config sim_config_id="S285.1">
        <mcc>460</mcc>
        <mnc>01</mnc>
    </service_provider_sim_config>
    <service_provider_sim_config sim_config_id="S285.2">
        <mcc>460</mcc>
        <mnc>09</mnc>
    </service_provider_sim_config>
    <service_provider_sim_config sim_config_id="S286.2">
        <mcc>655</mcc>
        <mnc>10</mnc>
    </service_provider_sim_config>
    <service_provider_sim_config sim_config_id="S287.1">
        <mcc>655</mcc>
        <mnc>07</mnc>
        <sp>Cell C</sp>
    </service_provider_sim_config>
    <service_provider_sim_config sim_config_id="S288.1">
        <mcc>655</mcc>
        <mnc>01</mnc>
    </service_provider_sim_config>
    <service_provider_sim_config sim_config_id="S314.1">
        <mcc>420</mcc>
        <mnc>01</mnc>
    </service_provider_sim_config>
    <service_provider_sim_config sim_config_id="S319.1">
        <mcc>424</mcc>
        <mnc>02</mnc>
    </service_provider_sim_config>
    <service_provider_sim_config sim_config_id="S325.1">
        <mcc>452</mcc>
        <mnc>04</mnc>
    </service_provider_sim_config>
    <service_provider_sim_config sim_config_id="S343.1">
        <mcc>250</mcc>
        <mnc>20</mnc>
    </service_provider_sim_config>
    <service_provider_sim_config sim_config_id="S344.1">
        <mcc>250</mcc>
        <mnc>02</mnc>
    </service_provider_sim_config>
    <service_provider_sim_config sim_config_id="S346.1">
        <mcc>250</mcc>
        <mnc>01</mnc>
    </service_provider_sim_config>
    <service_provider_sim_config sim_config_id="S351.1">
        <mcc>250</mcc>
        <mnc>99</mnc>
    </service_provider_sim_config>
    <service_provider_sim_config sim_config_id="S366.1">
        <mcc>454</mcc>
        <mnc>00</mnc>
    </service_provider_sim_config>
    <service_provider_sim_config sim_config_id="S366.2">
        <mcc>454</mcc>
        <mnc>02</mnc>
    </service_provider_sim_config>
    <service_provider_sim_config sim_config_id="S366.3">
        <mcc>454</mcc>
        <mnc>10</mnc>
    </service_provider_sim_config>
    <service_provider_sim_config sim_config_id="S366.4">
        <mcc>454</mcc>
        <mnc>18</mnc>
    </service_provider_sim_config>
    <service_provider_sim_config sim_config_id="S366.5">
        <mcc>454</mcc>
        <mnc>00</mnc>
        <sp>1O1O</sp>
    </service_provider_sim_config>
    <service_provider_sim_config sim_config_id="S366.6">
        <mcc>454</mcc>
        <mnc>00</mnc>
        <sp>SUN Mobile</sp>
    </service_provider_sim_config>
    <service_provider_sim_config sim_config_id="S366.7">
        <mcc>454</mcc>
        <mnc>00</mnc>
        <sp>csl.</sp>
    </service_provider_sim_config>
    <service_provider_sim_config sim_config_id="S366.8">
        <mcc>454</mcc>
        <mnc>02</mnc>
        <sp>1O1O</sp>
    </service_provider_sim_config>
    <service_provider_sim_config sim_config_id="S366.9">
        <mcc>454</mcc>
        <mnc>02</mnc>
        <sp>SUN Mobile</sp>
    </service_provider_sim_config>
    <service_provider_sim_config sim_config_id="S366.11">
        <mcc>454</mcc>
        <mnc>18</mnc>
        <sp>1O1O</sp>
    </service_provider_sim_config>
    <service_provider_sim_config sim_config_id="S366.12">
        <mcc>454</mcc>
        <mnc>18</mnc>
        <sp>SUN Mobile</sp>
    </service_provider_sim_config>
    <service_provider_sim_config sim_config_id="S366.16">
        <mcc>454</mcc>
        <mnc>02</mnc>
        <sp>csl.</sp>
    </service_provider_sim_config>
    <service_provider_sim_config sim_config_id="S366.17">
        <mcc>454</mcc>
        <mnc>18</mnc>
        <sp>csl.</sp>
    </service_provider_sim_config>
    <service_provider_sim_config sim_config_id="S366.18">
        <mcc>454</mcc>
        <mnc>00</mnc>
        <sp>csl</sp>
    </service_provider_sim_config>
    <service_provider_sim_config sim_config_id="S366.19">
        <mcc>454</mcc>
        <mnc>00</mnc>
        <sp>Club</sp>
    </service_provider_sim_config>
    <service_provider_sim_config sim_config_id="S366.20">
        <mcc>454</mcc>
        <mnc>02</mnc>
        <sp>Club</sp>
    </service_provider_sim_config>
    <service_provider_sim_config sim_config_id="S366.21">
        <mcc>454</mcc>
        <mnc>18</mnc>
        <sp>Club</sp>
    </service_provider_sim_config>
    <service_provider_sim_config sim_config_id="S367.1">
        <mcc>454</mcc>
        <mnc>03</mnc>
    </service_provider_sim_config>
    <service_provider_sim_config sim_config_id="S367.2">
        <mcc>454</mcc>
        <mnc>04</mnc>
    </service_provider_sim_config>
    <service_provider_sim_config sim_config_id="S367.3">
        <mcc>454</mcc>
        <mnc>05</mnc>
    </service_provider_sim_config>
    <service_provider_sim_config sim_config_id="S367.4">
        <mcc>454</mcc>
        <mnc>14</mnc>
    </service_provider_sim_config>
    <service_provider_sim_config sim_config_id="S367.5">
        <mcc>226</mcc>
        <mnc>03</mnc>
    </service_provider_sim_config>
    <service_provider_sim_config sim_config_id="S367.6">
        <mcc>232</mcc>
        <mnc>11</mnc>
        <sp>Sweden</sp>
    </service_provider_sim_config>
    <service_provider_sim_config sim_config_id="S369.1">
        <mcc>454</mcc>
        <mnc>06</mnc>
    </service_provider_sim_config>
    <service_provider_sim_config sim_config_id="S369.2">
        <mcc>454</mcc>
        <mnc>15</mnc>
    </service_provider_sim_config>
    <service_provider_sim_config sim_config_id="S369.3">
        <mcc>454</mcc>
        <mnc>17</mnc>
    </service_provider_sim_config>
    <service_provider_sim_config sim_config_id="S382.1">
        <mcc>724</mcc>
        <mnc>05</mnc>
    </service_provider_sim_config>
    <service_provider_sim_config sim_config_id="S388.1">
        <mcc>704</mcc>
        <mnc>01</mnc>
    </service_provider_sim_config>
    <service_provider_sim_config sim_config_id="S391.1">
        <mcc>706</mcc>
        <mnc>01</mnc>
    </service_provider_sim_config>
    <service_provider_sim_config sim_config_id="S394.1">
        <mcc>708</mcc>
        <mnc>001</mnc>
    </service_provider_sim_config>
    <service_provider_sim_config sim_config_id="S396.1">
        <mcc>710</mcc>
        <mnc>73</mnc>
    </service_provider_sim_config>
    <service_provider_sim_config sim_config_id="S396.2">
        <mcc>710</mcc>
        <mnc>21</mnc>
    </service_provider_sim_config>
    <service_provider_sim_config sim_config_id="S401.1">
        <mcc>730</mcc>
        <mnc>02</mnc>
    </service_provider_sim_config>
    <service_provider_sim_config sim_config_id="S402.1">
        <mcc>730</mcc>
        <mnc>03</mnc>
    </service_provider_sim_config>
    <service_provider_sim_config sim_config_id="S403.1">
        <mcc>732</mcc>
        <mnc>101</mnc>
    </service_provider_sim_config>
    <service_provider_sim_config sim_config_id="S405.1">
        <mcc>732</mcc>
        <mnc>123</mnc>
    </service_provider_sim_config>
    <service_provider_sim_config sim_config_id="S412.1">
        <mcc>716</mcc>
        <mnc>10</mnc>
    </service_provider_sim_config>
    <service_provider_sim_config sim_config_id="S413.1">
        <mcc>740</mcc>
        <mnc>01</mnc>
    </service_provider_sim_config>
    <service_provider_sim_config sim_config_id="S414.1">
        <mcc>740</mcc>
        <mnc>00</mnc>
    </service_provider_sim_config>
    <service_provider_sim_config sim_config_id="S437.1">
        <mcc>204</mcc>
    </service_provider_sim_config>
    <service_provider_sim_config sim_config_id="S461.1">
        <mcc>214</mcc>
    </service_provider_sim_config>
    <service_provider_sim_config sim_config_id="S462.1">
        <mcc>230</mcc>
    </service_provider_sim_config>
    <service_provider_sim_config sim_config_id="S465.1">
        <mcc>260</mcc>
    </service_provider_sim_config>
    <service_provider_sim_config sim_config_id="S467.1">
        <mcc>206</mcc>
    </service_provider_sim_config>
    <service_provider_sim_config sim_config_id="S478.1">
        <mcc>302</mcc>
        <mnc>500</mnc>
    </service_provider_sim_config>
    <service_provider_sim_config sim_config_id="S479.1">
        <mcc>716</mcc>
        <mnc>06</mnc>
    </service_provider_sim_config>
    <service_provider_sim_config sim_config_id="S508.1">
        <mcc>214</mcc>
        <mnc>03</mnc>
        <imsi>^21403[^5][0-9]*</imsi>
    </service_provider_sim_config>
    <service_provider_sim_config sim_config_id="S508.2">
        <mcc>214</mcc>
        <mnc>03</mnc>
        <sp>Orange</sp>
    </service_provider_sim_config>
    <service_provider_sim_config sim_config_id="S508.3">
        <mcc>214</mcc>
        <mnc>03</mnc>
    </service_provider_sim_config>
    <service_provider_sim_config sim_config_id="S514.2">
        <mcc>655</mcc>
        <mnc>07</mnc>
    </service_provider_sim_config>
    <service_provider_sim_config sim_config_id="S523.1">
        <mcc>405</mcc>
        <mnc>874</mnc>
    </service_provider_sim_config>
    <service_provider_sim_config sim_config_id="S523.2">
        <mcc>405</mcc>
        <mnc>840</mnc>
    </service_provider_sim_config>
    <service_provider_sim_config sim_config_id="S523.3">
        <mcc>405</mcc>
        <mnc>854</mnc>
    </service_provider_sim_config>
    <service_provider_sim_config sim_config_id="S523.4">
        <mcc>405</mcc>
        <mnc>855</mnc>
    </service_provider_sim_config>
    <service_provider_sim_config sim_config_id="S523.5">
        <mcc>405</mcc>
        <mnc>856</mnc>
    </service_provider_sim_config>
    <service_provider_sim_config sim_config_id="S523.6">
        <mcc>405</mcc>
        <mnc>857</mnc>
    </service_provider_sim_config>
    <service_provider_sim_config sim_config_id="S523.7">
        <mcc>405</mcc>
        <mnc>858</mnc>
    </service_provider_sim_config>
    <service_provider_sim_config sim_config_id="S523.8">
        <mcc>405</mcc>
        <mnc>859</mnc>
    </service_provider_sim_config>
    <service_provider_sim_config sim_config_id="S523.9">
        <mcc>405</mcc>
        <mnc>860</mnc>
    </service_provider_sim_config>
    <service_provider_sim_config sim_config_id="S523.10">
        <mcc>405</mcc>
        <mnc>861</mnc>
    </service_provider_sim_config>
    <service_provider_sim_config sim_config_id="S523.11">
        <mcc>405</mcc>
        <mnc>862</mnc>
    </service_provider_sim_config>
    <service_provider_sim_config sim_config_id="S523.12">
        <mcc>405</mcc>
        <mnc>863</mnc>
    </service_provider_sim_config>
    <service_provider_sim_config sim_config_id="S523.13">
        <mcc>405</mcc>
        <mnc>864</mnc>
    </service_provider_sim_config>
    <service_provider_sim_config sim_config_id="S523.14">
        <mcc>405</mcc>
        <mnc>865</mnc>
    </service_provider_sim_config>
    <service_provider_sim_config sim_config_id="S523.15">
        <mcc>405</mcc>
        <mnc>866</mnc>
    </service_provider_sim_config>
    <service_provider_sim_config sim_config_id="S523.16">
        <mcc>405</mcc>
        <mnc>867</mnc>
    </service_provider_sim_config>
    <service_provider_sim_config sim_config_id="S523.17">
        <mcc>405</mcc>
        <mnc>868</mnc>
    </service_provider_sim_config>
    <service_provider_sim_config sim_config_id="S523.18">
        <mcc>405</mcc>
        <mnc>869</mnc>
    </service_provider_sim_config>
    <service_provider_sim_config sim_config_id="S523.19">
        <mcc>405</mcc>
        <mnc>870</mnc>
    </service_provider_sim_config>
    <service_provider_sim_config sim_config_id="S523.20">
        <mcc>405</mcc>
        <mnc>871</mnc>
    </service_provider_sim_config>
    <service_provider_sim_config sim_config_id="S523.21">
        <mcc>405</mcc>
        <mnc>872</mnc>
    </service_provider_sim_config>
    <service_provider_sim_config sim_config_id="S523.22">
        <mcc>405</mcc>
        <mnc>873</mnc>
    </service_provider_sim_config>
    <service_provider_sim_config sim_config_id="S523.23">
        <mcc>405</mcc>
        <mnc>15</mnc>
    </service_provider_sim_config>
    <service_provider_sim_config sim_config_id="S523.24">
        <mcc>405</mcc>
        <mnc>01</mnc>
    </service_provider_sim_config>
    <service_provider_sim_config sim_config_id="S523.25">
        <mcc>405</mcc>
        <mnc>05</mnc>
    </service_provider_sim_config>
    <service_provider_sim_config sim_config_id="S523.26">
        <mcc>405</mcc>
        <mnc>06</mnc>
    </service_provider_sim_config>
    <service_provider_sim_config sim_config_id="S523.27">
        <mcc>405</mcc>
        <mnc>07</mnc>
    </service_provider_sim_config>
    <service_provider_sim_config sim_config_id="S523.28">
        <mcc>405</mcc>
        <mnc>09</mnc>
    </service_provider_sim_config>
    <service_provider_sim_config sim_config_id="S523.29">
        <mcc>405</mcc>
        <mnc>10</mnc>
    </service_provider_sim_config>
    <service_provider_sim_config sim_config_id="S523.30">
        <mcc>405</mcc>
        <mnc>11</mnc>
    </service_provider_sim_config>
    <service_provider_sim_config sim_config_id="S523.31">
        <mcc>405</mcc>
        <mnc>13</mnc>
    </service_provider_sim_config>
    <service_provider_sim_config sim_config_id="S523.32">
        <mcc>405</mcc>
        <mnc>18</mnc>
    </service_provider_sim_config>
    <service_provider_sim_config sim_config_id="S523.33">
        <mcc>405</mcc>
        <mnc>19</mnc>
    </service_provider_sim_config>
    <service_provider_sim_config sim_config_id="S523.34">
        <mcc>405</mcc>
        <mnc>20</mnc>
    </service_provider_sim_config>
    <service_provider_sim_config sim_config_id="S523.35">
        <mcc>405</mcc>
        <mnc>21</mnc>
    </service_provider_sim_config>
    <service_provider_sim_config sim_config_id="S523.36">
        <mcc>405</mcc>
        <mnc>22</mnc>
    </service_provider_sim_config>
    <service_provider_sim_config sim_config_id="S523.37">
        <mcc>404</mcc>
        <mnc>09</mnc>
    </service_provider_sim_config>
    <service_provider_sim_config sim_config_id="S523.38">
        <mcc>404</mcc>
        <mnc>18</mnc>
    </service_provider_sim_config>
    <service_provider_sim_config sim_config_id="S523.39">
        <mcc>404</mcc>
        <mnc>36</mnc>
    </service_provider_sim_config>
    <service_provider_sim_config sim_config_id="S523.40">
        <mcc>404</mcc>
        <mnc>50</mnc>
    </service_provider_sim_config>
    <service_provider_sim_config sim_config_id="S523.41">
        <mcc>404</mcc>
        <mnc>52</mnc>
    </service_provider_sim_config>
    <service_provider_sim_config sim_config_id="S523.42">
        <mcc>404</mcc>
        <mnc>67</mnc>
    </service_provider_sim_config>
    <service_provider_sim_config sim_config_id="S523.43">
        <mcc>404</mcc>
        <mnc>83</mnc>
    </service_provider_sim_config>
    <service_provider_sim_config sim_config_id="S523.44">
        <mcc>404</mcc>
        <mnc>85</mnc>
    </service_provider_sim_config>
    <service_provider_sim_config sim_config_id="S523.45">
        <mcc>404</mcc>
        <mnc>96</mnc>
    </service_provider_sim_config>
    <service_provider_sim_config sim_config_id="S523.46">
        <mcc>404</mcc>
        <mnc>10</mnc>
    </service_provider_sim_config>
    <service_provider_sim_config sim_config_id="S523.47">
        <mcc>404</mcc>
        <mnc>02</mnc>
    </service_provider_sim_config>
    <service_provider_sim_config sim_config_id="S523.48">
        <mcc>404</mcc>
        <mnc>03</mnc>
    </service_provider_sim_config>
    <service_provider_sim_config sim_config_id="S523.49">
        <mcc>404</mcc>
        <mnc>97</mnc>
    </service_provider_sim_config>
    <service_provider_sim_config sim_config_id="S523.50">
        <mcc>404</mcc>
        <mnc>92</mnc>
    </service_provider_sim_config>
    <service_provider_sim_config sim_config_id="S523.51">
        <mcc>404</mcc>
        <mnc>45</mnc>
    </service_provider_sim_config>
    <service_provider_sim_config sim_config_id="S523.52">
        <mcc>404</mcc>
        <mnc>31</mnc>
    </service_provider_sim_config>
    <service_provider_sim_config sim_config_id="S523.53">
        <mcc>404</mcc>
        <mnc>40</mnc>
    </service_provider_sim_config>
    <service_provider_sim_config sim_config_id="S523.54">
        <mcc>404</mcc>
        <mnc>49</mnc>
    </service_provider_sim_config>
    <service_provider_sim_config sim_config_id="S523.55">
        <mcc>404</mcc>
        <mnc>90</mnc>
    </service_provider_sim_config>
    <service_provider_sim_config sim_config_id="S523.56">
        <mcc>404</mcc>
        <mnc>98</mnc>
    </service_provider_sim_config>
    <service_provider_sim_config sim_config_id="S523.57">
        <mcc>404</mcc>
        <mnc>93</mnc>
    </service_provider_sim_config>
    <service_provider_sim_config sim_config_id="S523.58">
        <mcc>404</mcc>
        <mnc>94</mnc>
    </service_provider_sim_config>
    <service_provider_sim_config sim_config_id="S523.59">
        <mcc>404</mcc>
        <mnc>95</mnc>
    </service_provider_sim_config>
    <service_provider_sim_config sim_config_id="S523.60">
        <mcc>404</mcc>
        <mnc>70</mnc>
    </service_provider_sim_config>
    <service_provider_sim_config sim_config_id="S523.61">
        <mcc>405</mcc>
        <mnc>54</mnc>
    </service_provider_sim_config>
    <service_provider_sim_config sim_config_id="S523.62">
        <mcc>405</mcc>
        <mnc>53</mnc>
    </service_provider_sim_config>
    <service_provider_sim_config sim_config_id="S523.63">
        <mcc>405</mcc>
        <mnc>52</mnc>
    </service_provider_sim_config>
    <service_provider_sim_config sim_config_id="S523.64">
        <mcc>405</mcc>
        <mnc>51</mnc>
    </service_provider_sim_config>
    <service_provider_sim_config sim_config_id="S523.65">
        <mcc>405</mcc>
        <mnc>55</mnc>
    </service_provider_sim_config>
    <service_provider_sim_config sim_config_id="S523.66">
        <mcc>405</mcc>
        <mnc>56</mnc>
    </service_provider_sim_config>
    <service_provider_sim_config sim_config_id="S523.67">
        <mcc>404</mcc>
        <mnc>20</mnc>
    </service_provider_sim_config>
    <service_provider_sim_config sim_config_id="S523.68">
        <mcc>404</mcc>
        <mnc>05</mnc>
    </service_provider_sim_config>
    <service_provider_sim_config sim_config_id="S523.69">
        <mcc>404</mcc>
        <mnc>11</mnc>
    </service_provider_sim_config>
    <service_provider_sim_config sim_config_id="S523.70">
        <mcc>404</mcc>
        <mnc>30</mnc>
    </service_provider_sim_config>
    <service_provider_sim_config sim_config_id="S523.71">
        <mcc>404</mcc>
        <mnc>86</mnc>
    </service_provider_sim_config>
    <service_provider_sim_config sim_config_id="S523.72">
        <mcc>404</mcc>
        <mnc>84</mnc>
    </service_provider_sim_config>
    <service_provider_sim_config sim_config_id="S523.73">
        <mcc>404</mcc>
        <mnc>13</mnc>
    </service_provider_sim_config>
    <service_provider_sim_config sim_config_id="S523.74">
        <mcc>404</mcc>
        <mnc>88</mnc>
    </service_provider_sim_config>
    <service_provider_sim_config sim_config_id="S523.75">
        <mcc>405</mcc>
        <mnc>67</mnc>
    </service_provider_sim_config>
    <service_provider_sim_config sim_config_id="S523.76">
        <mcc>405</mcc>
        <mnc>66</mnc>
    </service_provider_sim_config>
    <service_provider_sim_config sim_config_id="S523.77">
        <mcc>404</mcc>
        <mnc>15</mnc>
    </service_provider_sim_config>
    <service_provider_sim_config sim_config_id="S523.78">
        <mcc>404</mcc>
        <mnc>01</mnc>
    </service_provider_sim_config>
    <service_provider_sim_config sim_config_id="S523.79">
        <mcc>404</mcc>
        <mnc>60</mnc>
    </service_provider_sim_config>
    <service_provider_sim_config sim_config_id="S523.80">
        <mcc>404</mcc>
        <mnc>46</mnc>
    </service_provider_sim_config>
    <service_provider_sim_config sim_config_id="S523.81">
        <mcc>404</mcc>
        <mnc>27</mnc>
    </service_provider_sim_config>
    <service_provider_sim_config sim_config_id="S523.82">
        <mcc>404</mcc>
        <mnc>43</mnc>
    </service_provider_sim_config>
    <service_provider_sim_config sim_config_id="S523.83">
        <mcc>405</mcc>
        <mnc>753</mnc>
    </service_provider_sim_config>
    <service_provider_sim_config sim_config_id="S523.84">
        <mcc>405</mcc>
        <mnc>751</mnc>
    </service_provider_sim_config>
    <service_provider_sim_config sim_config_id="S523.85">
        <mcc>405</mcc>
        <mnc>756</mnc>
    </service_provider_sim_config>
    <service_provider_sim_config sim_config_id="S523.86">
        <mcc>405</mcc>
        <mnc>752</mnc>
    </service_provider_sim_config>
    <service_provider_sim_config sim_config_id="S523.87">
        <mcc>405</mcc>
        <mnc>755</mnc>
    </service_provider_sim_config>
    <service_provider_sim_config sim_config_id="S523.88">
        <mcc>405</mcc>
        <mnc>754</mnc>
    </service_provider_sim_config>
    <service_provider_sim_config sim_config_id="S523.89">
        <mcc>405</mcc>
        <mnc>750</mnc>
    </service_provider_sim_config>
    <service_provider_sim_config sim_config_id="S527.1">
        <mcc>214</mcc>
        <mnc>03</mnc>
        <sp>EUSKALTEL</sp>
    </service_provider_sim_config>
    <service_provider_sim_config sim_config_id="S537.1">
        <mcc>214</mcc>
        <mnc>04</mnc>
        <sp>Yoigo</sp>
    </service_provider_sim_config>
    <service_provider_sim_config sim_config_id="S545.1">
        <mcc>454</mcc>
        <mnc>16</mnc>
    </service_provider_sim_config>
    <service_provider_sim_config sim_config_id="S545.2">
        <mcc>454</mcc>
        <mnc>19</mnc>
    </service_provider_sim_config>
    <service_provider_sim_config sim_config_id="S545.3">
        <mcc>454</mcc>
        <mnc>29</mnc>
    </service_provider_sim_config>
    <service_provider_sim_config sim_config_id="S567.1">
        <mcc>510</mcc>
        <mnc>89</mnc>
    </service_provider_sim_config>
    <service_provider_sim_config sim_config_id="S569.1">
        <mcc>231</mcc>
        <mnc>06</mnc>
    </service_provider_sim_config>
    <service_provider_sim_config sim_config_id="S573.1">
        <mcc>424</mcc>
        <mnc>03</mnc>
    </service_provider_sim_config>
    <service_provider_sim_config sim_config_id="S589.1">
        <mcc>216</mcc>
    </service_provider_sim_config>
    <service_provider_sim_config sim_config_id="S603.1">
        <mcc>370</mcc>
        <mnc>02</mnc>
    </service_provider_sim_config>
    <service_provider_sim_config sim_config_id="S605.1">
        <mcc>274</mcc>
        <mnc>02</mnc>
    </service_provider_sim_config>
    <service_provider_sim_config sim_config_id="S608.1">
        <mcc>440</mcc>
        <mnc>10</mnc>
    </service_provider_sim_config>
    <service_provider_sim_config sim_config_id="S622.2">
        <mcc>260</mcc>
        <mnc>06</mnc>
        <sp>PLAY PL</sp>
    </service_provider_sim_config>
    <service_provider_sim_config sim_config_id="S622.3">
        <mcc>260</mcc>
        <mnc>06</mnc>
        <sp>PLAY</sp>
    </service_provider_sim_config>
    <service_provider_sim_config sim_config_id="S622.4">
        <mcc>260</mcc>
        <mnc>06</mnc>
    </service_provider_sim_config>
    <service_provider_sim_config sim_config_id="S625.1">
        <mcc>220</mcc>
        <mnc>05</mnc>
    </service_provider_sim_config>
    <service_provider_sim_config sim_config_id="S628.1">
        <mcc>226</mcc>
    </service_provider_sim_config>
    <service_provider_sim_config sim_config_id="S674.1">
        <mcc>212</mcc>
        <mnc>10</mnc>
    </service_provider_sim_config>
    <service_provider_sim_config sim_config_id="S676.1">
        <mcc>647</mcc>
        <mnc>00</mnc>
    </service_provider_sim_config>
    <service_provider_sim_config sim_config_id="S687.1">
        <mcc>247</mcc>
        <mnc>05</mnc>
    </service_provider_sim_config>
    <service_provider_sim_config sim_config_id="S687.2">
        <mcc>246</mcc>
        <mnc>02</mnc>
    </service_provider_sim_config>
    <service_provider_sim_config sim_config_id="S700.1">
        <mcc>272</mcc>
        <mnc>11</mnc>
        <gid1>0A</gid1>
    </service_provider_sim_config>
    <service_provider_sim_config sim_config_id="S700.2">
        <mcc>206</mcc>
        <mnc>01</mnc>
        <gid1>0A</gid1>
    </service_provider_sim_config>
    <service_provider_sim_config sim_config_id="S4403.1">
        <mcc>293</mcc>
        <mnc>70</mnc>
    </service_provider_sim_config>
    <service_provider_sim_config sim_config_id="S4423.1">
        <mcc>340</mcc>
        <mnc>02</mnc>
    </service_provider_sim_config>
    <service_provider_sim_config sim_config_id="S4486.1">
        <mcc>214</mcc>
        <mnc>04</mnc>
        <sp>pepephone</sp>
    </service_provider_sim_config>
    <service_provider_sim_config sim_config_id="S4504.1">
        <mcc>502</mcc>
        <mnc>18</mnc>
    </service_provider_sim_config>
    <service_provider_sim_config sim_config_id="S4505.1">
        <mcc>650</mcc>
        <mnc>10</mnc>
    </service_provider_sim_config>
    <service_provider_sim_config sim_config_id="S4508.1">
        <mcc>425</mcc>
        <mnc>03</mnc>
        <sp>Pelephone</sp>
        <gid1>25</gid1>
        <imsi>42503</imsi>
    </service_provider_sim_config>
    <service_provider_sim_config sim_config_id="S4508.2">
        <mcc>425</mcc>
        <mnc>03</mnc>
        <sp>Pelephone</sp>
    </service_provider_sim_config>
    <service_provider_sim_config sim_config_id="S6325.1">
        <mcc>510</mcc>
        <mnc>01</mnc>
    </service_provider_sim_config>
    <service_provider_sim_config sim_config_id="S6325.2">
        <mcc>510</mcc>
        <mnc>21</mnc>
    </service_provider_sim_config>
    <service_provider_sim_config sim_config_id="S6333.1">
        <mcc>714</mcc>
        <mnc>03</mnc>
    </service_provider_sim_config>
    <service_provider_sim_config sim_config_id="S6334.3">
        <mcc>302</mcc>
        <mnc>610</mnc>
        <gid1>3D</gid1>
    </service_provider_sim_config>
    <service_provider_sim_config sim_config_id="S6334.4">
        <mcc>302</mcc>
        <mnc>630</mnc>
    </service_provider_sim_config>
    <service_provider_sim_config sim_config_id="S6334.5">
        <mcc>302</mcc>
        <mnc>640</mnc>
    </service_provider_sim_config>
    <service_provider_sim_config sim_config_id="S6335.3">
        <mcc>302</mcc>
        <mnc>220</mnc>
        <gid1>54</gid1>
    </service_provider_sim_config>
    <service_provider_sim_config sim_config_id="S6335.4">
        <mcc>302</mcc>
        <mnc>221</mnc>
        <gid1>54</gid1>
    </service_provider_sim_config>
    <service_provider_sim_config sim_config_id="S6552.1">
        <mcc>450</mcc>
        <mnc>05</mnc>
    </service_provider_sim_config>
    <service_provider_sim_config sim_config_id="S6565.1">
        <mcc>440</mcc>
        <mnc>50</mnc>
    </service_provider_sim_config>
    <service_provider_sim_config sim_config_id="S6565.2">
        <mcc>440</mcc>
        <mnc>51</mnc>
    </service_provider_sim_config>
    <service_provider_sim_config sim_config_id="S6570.1">
        <mcc>232</mcc>
        <mnc>12</mnc>
    </service_provider_sim_config>
    <service_provider_sim_config sim_config_id="S8271.1">
        <mcc>901</mcc>
        <mnc>12</mnc>
        <sp>Just for Test</sp>
    </service_provider_sim_config>
    <service_provider_sim_config sim_config_id="S8271.2">
        <mcc>208</mcc>
        <mnc>10</mnc>
        <sp>CT TEst</sp>
    </service_provider_sim_config>
    <service_provider_sim_config sim_config_id="S8603.1">
        <mcc>284</mcc>
        <mnc>03</mnc>
    </service_provider_sim_config>
    <service_provider_sim_config sim_config_id="S8604.1">
        <mcc>238</mcc>
        <mnc>20</mnc>
        <sp>Call me</sp>
    </service_provider_sim_config>
    <service_provider_sim_config sim_config_id="S8605.1">
        <mcc>334</mcc>
        <mnc>050</mnc>
    </service_provider_sim_config>
    <service_provider_sim_config sim_config_id="S8605.2">
        <mcc>334</mcc>
        <mnc>090</mnc>
    </service_provider_sim_config>
    <service_provider_sim_config sim_config_id="S8605.5">
        <mcc>334</mcc>
        <mnc>05</mnc>
    </service_provider_sim_config>
    <service_provider_sim_config sim_config_id="S8611.1">
        <mcc>232</mcc>
        <mnc>11</mnc>
    </service_provider_sim_config>
    <service_provider_sim_config sim_config_id="S8620.1">
        <mcc>311</mcc>
        <mnc>480</mnc>
    </service_provider_sim_config>
    <service_provider_sim_config sim_config_id="S8620.2">
        <mcc>204</mcc>
        <mnc>04</mnc>
        <gid1>BAE0000000000000</gid1>
    </service_provider_sim_config>
    <service_provider_sim_config sim_config_id="S8626.1">
        <mcc>204</mcc>
        <mnc>02</mnc>
    </service_provider_sim_config>
    <service_provider_sim_config sim_config_id="S8626.2">
        <mcc>204</mcc>
        <mnc>02</mnc>
        <imsi>^20402\s?(([7-8]([0]|[5])[0])|([9][0][0-6])).*</imsi>
    </service_provider_sim_config>
    <service_provider_sim_config sim_config_id="S8626.3">
        <mcc>204</mcc>
        <mnc>02</mnc>
        <imsi>^240076\s?([0]([2-3]|[8])|[1]([0-1]|[3-8])).*</imsi>
    </service_provider_sim_config>
    <service_provider_sim_config sim_config_id="S8626.4">
        <mcc>204</mcc>
        <mnc>02</mnc>
        <imsi>^20402\s?([0]([2-3]|[8])|[1]([0-1]|[3-8])).*</imsi>
    </service_provider_sim_config>
    <service_provider_sim_config sim_config_id="S8636.1">
        <mcc>655</mcc>
        <mnc>02</mnc>
    </service_provider_sim_config>
    <service_provider_sim_config sim_config_id="S8638.1">
        <mcc>206</mcc>
        <mnc>05</mnc>
    </service_provider_sim_config>
    <service_provider_sim_config sim_config_id="S8655.1">
        <mcc>262</mcc>
        <mnc>01</mnc>
    </service_provider_sim_config>
    <service_provider_sim_config sim_config_id="S8655.4">
        <mcc>262</mcc>
        <mnc>01</mnc>
        <gid1>01</gid1>
    </service_provider_sim_config>
    <service_provider_sim_config sim_config_id="S8655.5">
        <mcc>262</mcc>
        <mnc>01</mnc>
        <gid1>02</gid1>
    </service_provider_sim_config>
    <service_provider_sim_config sim_config_id="S8655.6">
        <mcc>262</mcc>
        <mnc>01</mnc>
        <gid1>03</gid1>
    </service_provider_sim_config>
    <service_provider_sim_config sim_config_id="S8655.7">
        <mcc>262</mcc>
        <mnc>01</mnc>
        <gid1>99</gid1>
    </service_provider_sim_config>
    <service_provider_sim_config sim_config_id="S8657.1">
        <mcc>260</mcc>
        <mnc>02</mnc>
    </service_provider_sim_config>
    <service_provider_sim_config sim_config_id="S8663.1">
        <mcc>001</mcc>
        <mnc>01</mnc>
    </service_provider_sim_config>
    <service_provider_sim_config sim_config_id="S8663.2">
        <mcc>001</mcc>
        <mnc>010</mnc>
    </service_provider_sim_config>
    <service_provider_sim_config sim_config_id="S8663.3">
        <mcc>001</mcc>
        <mnc>012</mnc>
    </service_provider_sim_config>
    <service_provider_sim_config sim_config_id="S8667.1">
        <mcc>293</mcc>
        <mnc>64</mnc>
    </service_provider_sim_config>
    <service_provider_sim_config sim_config_id="S8668.1">
        <mcc>712</mcc>
        <mnc>03</mnc>
    </service_provider_sim_config>
    <service_provider_sim_config sim_config_id="S8669.1">
        <mcc>214</mcc>
        <mnc>06</mnc>
        <sp>mobilR</sp>
    </service_provider_sim_config>
    <service_provider_sim_config sim_config_id="S8669.2">
        <mcc>214</mcc>
        <mnc>03</mnc>
        <imsi>21403508</imsi>
    </service_provider_sim_config>
    <service_provider_sim_config sim_config_id="S8669.3">
        <mcc>214</mcc>
        <mnc>03</mnc>
        <imsi>21403509</imsi>
    </service_provider_sim_config>
    <service_provider_sim_config sim_config_id="S8669.4">
        <mcc>214</mcc>
        <mnc>03</mnc>
        <sp>mobilR</sp>
    </service_provider_sim_config>
    <service_provider_sim_config sim_config_id="S8669.5">
        <mcc>214</mcc>
        <mnc>03</mnc>
        <sp>mobil R</sp>
    </service_provider_sim_config>
    <service_provider_sim_config sim_config_id="S8669.6">
        <mcc>214</mcc>
        <mnc>03</mnc>
        <imsi>21403508.*</imsi>
    </service_provider_sim_config>
    <service_provider_sim_config sim_config_id="S8669.7">
        <mcc>214</mcc>
        <mnc>03</mnc>
        <imsi>21403509.*</imsi>
    </service_provider_sim_config>
    <service_provider_sim_config sim_config_id="S8680.3">
        <mcc>302</mcc>
        <mnc>720</mnc>
        <imsi>30272094</imsi>
    </service_provider_sim_config>
    <service_provider_sim_config sim_config_id="S8680.4">
        <mcc>302</mcc>
        <mnc>720</mnc>
        <imsi>\d{7}94\d+</imsi>
    </service_provider_sim_config>
    <service_provider_sim_config sim_config_id="S8680.5">
        <mcc>302</mcc>
        <mnc>720</mnc>
        <gid1>D2</gid1>
    </service_provider_sim_config>
    <service_provider_sim_config sim_config_id="S8683.1">
        <mcc>208</mcc>
        <mnc>15</mnc>
    </service_provider_sim_config>
    <service_provider_sim_config sim_config_id="S8684.1">
        <mcc>214</mcc>
        <mnc>03</mnc>
        <sp>RACC</sp>
    </service_provider_sim_config>
    <service_provider_sim_config sim_config_id="S8686.1">
        <mcc>214</mcc>
        <mnc>04</mnc>
        <sp>telecable</sp>
    </service_provider_sim_config>
    <service_provider_sim_config sim_config_id="S8686.2">
        <mcc>214</mcc>
        <mnc>16</mnc>
    </service_provider_sim_config>
    <service_provider_sim_config sim_config_id="S8686.3">
        <mcc>214</mcc>
        <mnc>05</mnc>
        <sp>telecable</sp>
    </service_provider_sim_config>
    <service_provider_sim_config sim_config_id="S8704.1">
        <mcc>520</mcc>
        <mnc>00</mnc>
    </service_provider_sim_config>
    <service_provider_sim_config sim_config_id="S8704.2">
        <mcc>520</mcc>
        <mnc>04</mnc>
    </service_provider_sim_config>
    <service_provider_sim_config sim_config_id="S8723.1">
        <mcc>204</mcc>
        <mnc>16</mnc>
        <sp>Ben NL</sp>
    </service_provider_sim_config>
    <service_provider_sim_config sim_config_id="S8726.1">
        <mcc>425</mcc>
        <mnc>01</mnc>
    </service_provider_sim_config>
    <service_provider_sim_config sim_config_id="S8726.2">
        <mcc>425</mcc>
        <mnc>07</mnc>
    </service_provider_sim_config>
    <service_provider_sim_config sim_config_id="S8729.1">
        <mcc>214</mcc>
        <mnc>18</mnc>
    </service_provider_sim_config>
    <service_provider_sim_config sim_config_id="S8738.1">
        <mcc>302</mcc>
        <mnc>490</mnc>
    </service_provider_sim_config>
    <service_provider_sim_config sim_config_id="S8739.1">
        <mcc>302</mcc>
        <mnc>660</mnc>
    </service_provider_sim_config>
    <service_provider_sim_config sim_config_id="S8739.2">
        <mcc>302</mcc>
        <mnc>370</mnc>
        <gid1>2C</gid1>
    </service_provider_sim_config>
    <service_provider_sim_config sim_config_id="S8739.3">
        <mcc>302</mcc>
        <mnc>660</mnc>
        <gid1>2C</gid1>
    </service_provider_sim_config>
    <service_provider_sim_config sim_config_id="S8741.1">
        <mcc>302</mcc>
        <mnc>270</mnc>
    </service_provider_sim_config>
    <service_provider_sim_config sim_config_id="S8752.1">
        <mcc>214</mcc>
        <mnc>21</mnc>
        <sp>JAZZTEL</sp>
    </service_provider_sim_config>
    <service_provider_sim_config sim_config_id="S8752.2">
        <mcc>214</mcc>
        <mnc>07</mnc>
        <sp>JAZZTEL</sp>
    </service_provider_sim_config>
    <service_provider_sim_config sim_config_id="S8752.3">
        <mcc>214</mcc>
        <mnc>03</mnc>
        <sp>JAZZTEL</sp>
    </service_provider_sim_config>
    <service_provider_sim_config sim_config_id="S8752.4">
        <mcc>214</mcc>
        <mnc>03</mnc>
        <sp>JAZZTEL</sp>
        <imsi>^21403[^5][0-9]*</imsi>
    </service_provider_sim_config>
    <service_provider_sim_config sim_config_id="S8752.5">
        <mcc>214</mcc>
        <mnc>03</mnc>
        <sp>JAZZTEL</sp>
        <imsi>21403503</imsi>
    </service_provider_sim_config>
    <service_provider_sim_config sim_config_id="S8752.6">
        <mcc>214</mcc>
        <mnc>03</mnc>
        <sp>JAZZTEL</sp>
        <imsi>21403504</imsi>
    </service_provider_sim_config>
    <service_provider_sim_config sim_config_id="S8753.1">
        <mcc>214</mcc>
        <mnc>03</mnc>
        <sp>simyo</sp>
    </service_provider_sim_config>
    <service_provider_sim_config sim_config_id="S8753.2">
        <mcc>214</mcc>
        <mnc>03</mnc>
        <sp>simyo</sp>
        <imsi>2140358</imsi>
    </service_provider_sim_config>
    <service_provider_sim_config sim_config_id="S8753.3">
        <mcc>214</mcc>
        <mnc>19</mnc>
        <sp>simyo</sp>
    </service_provider_sim_config>
    <service_provider_sim_config sim_config_id="S8760.1">
        <mcc>460</mcc>
        <mnc>03</mnc>
    </service_provider_sim_config>
    <service_provider_sim_config sim_config_id="S8760.2">
        <mcc>460</mcc>
        <mnc>11</mnc>
    </service_provider_sim_config>
    <service_provider_sim_config sim_config_id="S8765.1">
        <mcc>450</mcc>
        <mnc>08</mnc>
    </service_provider_sim_config>
    <service_provider_sim_config sim_config_id="S8768.1">
        <mcc>284</mcc>
    </service_provider_sim_config>
    <service_provider_sim_config sim_config_id="S8768.2">
        <mcc>226</mcc>
    </service_provider_sim_config>
    <service_provider_sim_config sim_config_id="S8768.3">
        <mcc>259</mcc>
    </service_provider_sim_config>
    <service_provider_sim_config sim_config_id="S8773.1">
        <mcc>234</mcc>
        <mnc>33</mnc>
    </service_provider_sim_config>
    <service_provider_sim_config sim_config_id="S8777.2">
        <mcc>302</mcc>
        <mnc>610</mnc>
        <gid1>3E</gid1>
    </service_provider_sim_config>
    <service_provider_sim_config sim_config_id="S8779.1">
        <mcc>466</mcc>
        <mnc>05</mnc>
    </service_provider_sim_config>
    <service_provider_sim_config sim_config_id="S8779.2">
        <mcc>525</mcc>
        <mnc>05</mnc>
        <gid1>0A</gid1>
    </service_provider_sim_config>
    <service_provider_sim_config sim_config_id="S8779.5">
        <mcc>525</mcc>
        <mnc>05</mnc>
        <gid1>0AFFFFFF</gid1>
    </service_provider_sim_config>
    <service_provider_sim_config sim_config_id="S8779.6">
        <mcc>525</mcc>
        <mnc>05</mnc>
        <gid1>0AFFFFFFFFFFFFFF</gid1>
    </service_provider_sim_config>
    <service_provider_sim_config sim_config_id="S8827.1">
        <mcc>284</mcc>
    </service_provider_sim_config>
    <service_provider_sim_config sim_config_id="S8828.1">
        <mcc>231</mcc>
    </service_provider_sim_config>
    <service_provider_sim_config sim_config_id="S8897.2">
        <mcc>302</mcc>
        <mnc>610</mnc>
        <gid1>3F</gid1>
    </service_provider_sim_config>
    <service_provider_sim_config sim_config_id="S8898.2">
        <mcc>302</mcc>
        <mnc>610</mnc>
        <gid1>40</gid1>
    </service_provider_sim_config>
    <service_provider_sim_config sim_config_id="S8903.3">
        <mcc>302</mcc>
        <mnc>720</mnc>
        <imsi>30272097</imsi>
    </service_provider_sim_config>
    <service_provider_sim_config sim_config_id="S8903.4">
        <mcc>302</mcc>
        <mnc>720</mnc>
        <imsi>\d{7}97\d+</imsi>
    </service_provider_sim_config>
    <service_provider_sim_config sim_config_id="S8903.5">
        <mcc>302</mcc>
        <mnc>720</mnc>
        <gid1>CC</gid1>
    </service_provider_sim_config>
    <service_provider_sim_config sim_config_id="S8904.3">
        <mcc>302</mcc>
        <mnc>720</mnc>
        <imsi>30272092</imsi>
    </service_provider_sim_config>
    <service_provider_sim_config sim_config_id="S8904.4">
        <mcc>302</mcc>
        <mnc>720</mnc>
        <imsi>\d{7}92\d+</imsi>
    </service_provider_sim_config>
    <service_provider_sim_config sim_config_id="S8904.5">
        <mcc>302</mcc>
        <mnc>720</mnc>
        <gid1>BA</gid1>
    </service_provider_sim_config>
    <service_provider_sim_config sim_config_id="S8909.2">
        <mcc>302</mcc>
        <mnc>220</mnc>
        <gid1>50</gid1>
    </service_provider_sim_config>
    <service_provider_sim_config sim_config_id="S8909.3">
        <mcc>302</mcc>
        <mnc>220</mnc>
        <gid1>4D</gid1>
    </service_provider_sim_config>
    <service_provider_sim_config sim_config_id="S8909.4">
        <mcc>302</mcc>
        <mnc>220</mnc>
        <gid1>43</gid1>
    </service_provider_sim_config>
    <service_provider_sim_config sim_config_id="S8912.1">
        <mcc>302</mcc>
        <mnc>780</mnc>
    </service_provider_sim_config>
    <service_provider_sim_config sim_config_id="S8912.2">
        <mcc>204</mcc>
        <mnc>04</mnc>
        <gid1>5A</gid1>
    </service_provider_sim_config>
    <service_provider_sim_config sim_config_id="S8913.2">
        <mcc>302</mcc>
        <mnc>220</mnc>
        <gid1>4B</gid1>
    </service_provider_sim_config>
    <service_provider_sim_config sim_config_id="S8938.1">
        <mcc>716</mcc>
        <mnc>17</mnc>
    </service_provider_sim_config>
    <service_provider_sim_config sim_config_id="S8957.1">
        <mcc>310</mcc>
        <mnc>260</mnc>
        <gid1>6D</gid1>
    </service_provider_sim_config>
    <service_provider_sim_config sim_config_id="S8957.2">
        <mcc>310</mcc>
        <mnc>160</mnc>
        <gid1>6D</gid1>
    </service_provider_sim_config>
    <service_provider_sim_config sim_config_id="S8957.3">
        <mcc>310</mcc>
        <mnc>200</mnc>
        <gid1>6D</gid1>
    </service_provider_sim_config>
    <service_provider_sim_config sim_config_id="S8957.4">
        <mcc>310</mcc>
        <mnc>210</mnc>
        <gid1>6D</gid1>
    </service_provider_sim_config>
    <service_provider_sim_config sim_config_id="S8957.5">
        <mcc>310</mcc>
        <mnc>220</mnc>
        <gid1>6D</gid1>
    </service_provider_sim_config>
    <service_provider_sim_config sim_config_id="S8957.6">
        <mcc>310</mcc>
        <mnc>230</mnc>
        <gid1>6D</gid1>
    </service_provider_sim_config>
    <service_provider_sim_config sim_config_id="S8957.7">
        <mcc>310</mcc>
        <mnc>240</mnc>
        <gid1>6D</gid1>
    </service_provider_sim_config>
    <service_provider_sim_config sim_config_id="S8957.8">
        <mcc>310</mcc>
        <mnc>250</mnc>
        <gid1>6D</gid1>
    </service_provider_sim_config>
    <service_provider_sim_config sim_config_id="S8957.9">
        <mcc>310</mcc>
        <mnc>270</mnc>
        <gid1>6D</gid1>
    </service_provider_sim_config>
    <service_provider_sim_config sim_config_id="S8957.10">
        <mcc>310</mcc>
        <mnc>310</mnc>
        <gid1>6D</gid1>
    </service_provider_sim_config>
    <service_provider_sim_config sim_config_id="S8957.11">
        <mcc>310</mcc>
        <mnc>490</mnc>
        <gid1>6D</gid1>
    </service_provider_sim_config>
    <service_provider_sim_config sim_config_id="S8957.12">
        <mcc>310</mcc>
        <mnc>530</mnc>
        <gid1>6D</gid1>
    </service_provider_sim_config>
    <service_provider_sim_config sim_config_id="S8957.13">
        <mcc>310</mcc>
        <mnc>590</mnc>
        <gid1>6D</gid1>
    </service_provider_sim_config>
    <service_provider_sim_config sim_config_id="S8957.14">
        <mcc>310</mcc>
        <mnc>640</mnc>
        <gid1>6D</gid1>
    </service_provider_sim_config>
    <service_provider_sim_config sim_config_id="S8957.15">
        <mcc>310</mcc>
        <mnc>660</mnc>
        <gid1>6D</gid1>
    </service_provider_sim_config>
    <service_provider_sim_config sim_config_id="S8957.16">
        <mcc>310</mcc>
        <mnc>800</mnc>
        <gid1>6D</gid1>
    </service_provider_sim_config>
    <service_provider_sim_config sim_config_id="S8957.17">
        <mcc>310</mcc>
        <mnc>300</mnc>
        <gid1>6D</gid1>
    </service_provider_sim_config>
    <service_provider_sim_config sim_config_id="S8960.1">
        <mcc>262</mcc>
        <mnc>01</mnc>
        <sp>congstar</sp>
    </service_provider_sim_config>
    <service_provider_sim_config sim_config_id="S8960.2">
        <mcc>262</mcc>
        <mnc>01</mnc>
        <sp>congstar.de</sp>
    </service_provider_sim_config>
    <service_provider_sim_config sim_config_id="S8981.1">
        <mcc>440</mcc>
        <mnc>20</mnc>
        <sp>Softbank</sp>
    </service_provider_sim_config>
    <service_provider_sim_config sim_config_id="S8981.2">
        <mcc>440</mcc>
        <mnc>20</mnc>
        <sp>Disney</sp>
    </service_provider_sim_config>
    <service_provider_sim_config sim_config_id="S8981.3">
        <mcc>440</mcc>
        <mnc>20</mnc>
        <sp>Softbank_Biz1</sp>
    </service_provider_sim_config>
    <service_provider_sim_config sim_config_id="S8981.4">
        <mcc>440</mcc>
        <mnc>20</mnc>
        <sp>Softbank_Biz2</sp>
    </service_provider_sim_config>
    <service_provider_sim_config sim_config_id="S8981.5">
        <mcc>440</mcc>
        <mnc>20</mnc>
        <sp>Softbank_Biz3</sp>
    </service_provider_sim_config>
    <service_provider_sim_config sim_config_id="S8981.6">
        <mcc>440</mcc>
        <mnc>20</mnc>
        <sp>Ymobile</sp>
    </service_provider_sim_config>
    <service_provider_sim_config sim_config_id="S8981.7">
        <mcc>440</mcc>
        <mnc>20</mnc>
    </service_provider_sim_config>
    <service_provider_sim_config sim_config_id="S8981.8">
        <mcc>440</mcc>
        <mnc>00</mnc>
    </service_provider_sim_config>
    <service_provider_sim_config sim_config_id="S9002.1">
        <mcc>226</mcc>
        <mnc>03</mnc>
    </service_provider_sim_config>
    <service_provider_sim_config sim_config_id="S9002.2">
        <mcc>226</mcc>
        <mnc>06</mnc>
    </service_provider_sim_config>
    <service_provider_sim_config sim_config_id="S9033.1">
        <mcc>234</mcc>
        <mnc>20</mnc>
        <sp>iD</sp>
    </service_provider_sim_config>
    <service_provider_sim_config sim_config_id="S9050.1">
        <mcc>220</mcc>
        <mnc>02</mnc>
    </service_provider_sim_config>
    <service_provider_sim_config sim_config_id="S9052.1">
        <mcc>231</mcc>
        <mnc>03</mnc>
    </service_provider_sim_config>
    <service_provider_sim_config sim_config_id="S9064.1">
        <mcc>454</mcc>
        <mnc>12</mnc>
    </service_provider_sim_config>
    <service_provider_sim_config sim_config_id="S9064.2">
        <mcc>454</mcc>
        <mnc>13</mnc>
    </service_provider_sim_config>
    <service_provider_sim_config sim_config_id="S9064.3">
        <mcc>454</mcc>
        <mnc>09</mnc>
    </service_provider_sim_config>
    <service_provider_sim_config sim_config_id="S9065.2">
        <mcc>455</mcc>
        <mnc>01</mnc>
    </service_provider_sim_config>
    <service_provider_sim_config sim_config_id="S9065.3">
        <mcc>455</mcc>
        <mnc>04</mnc>
    </service_provider_sim_config>
    <service_provider_sim_config sim_config_id="S9078.1">
        <mcc>510</mcc>
        <mnc>09</mnc>
    </service_provider_sim_config>
    <service_provider_sim_config sim_config_id="S9078.2">
        <mcc>510</mcc>
        <mnc>28</mnc>
    </service_provider_sim_config>
    <service_provider_sim_config sim_config_id="S9083.1">
        <mcc>502</mcc>
        <mnc>152</mnc>
    </service_provider_sim_config>
    <service_provider_sim_config sim_config_id="S9087.1">
        <mcc>204</mcc>
        <mnc>12</mnc>
    </service_provider_sim_config>
    <service_provider_sim_config sim_config_id="S9089.1">
        <mcc>450</mcc>
        <mnc>06</mnc>
    </service_provider_sim_config>
    <service_provider_sim_config sim_config_id="S9093.1">
        <mcc>242</mcc>
        <mnc>14</mnc>
    </service_provider_sim_config>
    <service_provider_sim_config sim_config_id="S9095.1">
        <mcc>272</mcc>
        <mnc>15</mnc>
        <sp>Virgin Media IE</sp>
    </service_provider_sim_config>
    <service_provider_sim_config sim_config_id="S9095.2">
        <mcc>206</mcc>
        <mnc>01</mnc>
        <sp>Virgin Media IE</sp>
    </service_provider_sim_config>
    <service_provider_sim_config sim_config_id="S9105.1">
        <mcc>240</mcc>
        <mnc>02</mnc>
        <sp>hallon</sp>
    </service_provider_sim_config>
    <service_provider_sim_config sim_config_id="S9111.1">
        <mcc>242</mcc>
        <mnc>05</mnc>
    </service_provider_sim_config>
    <service_provider_sim_config sim_config_id="S9112.1">
        <mcc>234</mcc>
        <mnc>57</mnc>
    </service_provider_sim_config>
    <service_provider_sim_config sim_config_id="S9112.2">
        <mcc>240</mcc>
        <mnc>07</mnc>
        <gid1>0C</gid1>
    </service_provider_sim_config>
    <service_provider_sim_config sim_config_id="S9115.1">
        <mcc>655</mcc>
        <mnc>02</mnc>
        <sp>Telkom</sp>
    </service_provider_sim_config>
    <service_provider_sim_config sim_config_id="S9116.1">
        <mcc>204</mcc>
        <mnc>69</mnc>
    </service_provider_sim_config>
    <service_provider_sim_config sim_config_id="S9117.1">
        <mcc>302</mcc>
        <mnc>720</mnc>
        <imsi>\d{7}98\d+</imsi>
    </service_provider_sim_config>
    <service_provider_sim_config sim_config_id="S9117.2">
        <mcc>302</mcc>
        <mnc>720</mnc>
        <gid1>D4</gid1>
    </service_provider_sim_config>
    <service_provider_sim_config sim_config_id="S9119.1">
        <mcc>740</mcc>
        <mnc>02</mnc>
    </service_provider_sim_config>
    <service_provider_sim_config sim_config_id="S9125.1">
        <mcc>455</mcc>
        <mnc>03</mnc>
    </service_provider_sim_config>
    <service_provider_sim_config sim_config_id="S9125.2">
        <mcc>455</mcc>
        <mnc>05</mnc>
    </service_provider_sim_config>
    <service_provider_sim_config sim_config_id="S9126.1">
        <mcc>234</mcc>
        <mnc>30</mnc>
        <gid1>B3</gid1>
    </service_provider_sim_config>
    <service_provider_sim_config sim_config_id="S9126.2">
        <mcc>234</mcc>
        <mnc>30</mnc>
        <gid1>C3</gid1>
    </service_provider_sim_config>
    <service_provider_sim_config sim_config_id="S9127.1">
        <mcc>238</mcc>
        <mnc>01</mnc>
        <imsi>2380171</imsi>
    </service_provider_sim_config>
    <service_provider_sim_config sim_config_id="S9127.2">
        <mcc>242</mcc>
        <mnc>08</mnc>
        <imsi>24208xxxxxxxxxx</imsi>
    </service_provider_sim_config>
    <service_provider_sim_config sim_config_id="S9127.3">
        <mcc>242</mcc>
        <mnc>08</mnc>
    </service_provider_sim_config>
    <service_provider_sim_config sim_config_id="S9129.1">
        <mcc>222</mcc>
        <mnc>01</mnc>
        <sp>Coop Mobile</sp>
    </service_provider_sim_config>
    <service_provider_sim_config sim_config_id="S9130.1">
        <mcc>302</mcc>
        <mnc>610</mnc>
        <gid1>42</gid1>
    </service_provider_sim_config>
    <service_provider_sim_config sim_config_id="S9136.1">
        <mcc>302</mcc>
        <mnc>220</mnc>
        <gid1>4F</gid1>
    </service_provider_sim_config>
    <service_provider_sim_config sim_config_id="S9138.1">
        <mcc>226</mcc>
        <mnc>05</mnc>
    </service_provider_sim_config>
    <service_provider_sim_config sim_config_id="S9139.1">
        <mcc>216</mcc>
        <mnc>03</mnc>
    </service_provider_sim_config>
    <service_provider_sim_config sim_config_id="S9142.1">
        <mcc>216</mcc>
        <mnc>71</mnc>
    </service_provider_sim_config>
    <service_provider_sim_config sim_config_id="S9145.1">
        <mcc>222</mcc>
        <mnc>07</mnc>
        <sp>KENA MOBILE</sp>
    </service_provider_sim_config>
    <service_provider_sim_config sim_config_id="S9145.2">
        <mcc>222</mcc>
        <mnc>01</mnc>
        <sp>KENA MOBILE R</sp>
    </service_provider_sim_config>
    <service_provider_sim_config sim_config_id="S9145.3">
        <mcc>222</mcc>
        <mnc>07</mnc>
        <sp>^(?i)KENA MOBILE</sp>
    </service_provider_sim_config>
    <service_provider_sim_config sim_config_id="S9145.4">
        <mcc>222</mcc>
        <mnc>01</mnc>
        <sp>^(?i)KENA MOBILE R</sp>
    </service_provider_sim_config>
    <service_provider_sim_config sim_config_id="S9154.1">
        <mcc>259</mcc>
    </service_provider_sim_config>
    <service_provider_sim_config sim_config_id="S9161.1">
        <mcc>238</mcc>
        <mnc>20</mnc>
        <sp>Mit Tele</sp>
    </service_provider_sim_config>
    <service_provider_sim_config sim_config_id="S9162.1">
        <mcc>238</mcc>
        <mnc>20</mnc>
        <sp>Ditmobilselskab</sp>
    </service_provider_sim_config>
    <service_provider_sim_config sim_config_id="S9162.2">
        <mcc>238</mcc>
        <mnc>20</mnc>
        <imsi>2382089</imsi>
    </service_provider_sim_config>
    <service_provider_sim_config sim_config_id="S9163.1">
        <mcc>502</mcc>
        <mnc>153</mnc>
    </service_provider_sim_config>
</service_provider_sim_configs>